<!--Searching something similar to MRG32k3a, but with 64 bits-->
<seek>
  <gen>
    <numcomp x="2"/>
    <mrg>
      <modulo basis="2" exponent="63" rest="-21129"/>
      <order x="3"/>
      <method random="1 0 1"/>
      <period check="true"/>
    </mrg>
    <mrg>
      <modulo basis="2" exponent="63" rest="-275025"/>
      <order x="3"/>
      <method random="0 1 1"/>
      <period check="true"/>
    </mrg>
  </gen>
  <spectral>
    <reduction method="FULL"/>
    <norma x="BESTLAT"/>
    <dual x="true"/>
  </spectral>
  <proj>
    <min x="4"/>
    <num x="1"/>
    <dim x="35"/>
  </proj>
  <time x="120"/>
  <num_gen x="5"/>
</seek>
<out/>
